whyis_milvus/__init__.py
whyis_milvus/_version.py
whyis_milvus/plugin.py
whyis_milvus/entity_linker/__init__.py
whyis_milvus/entity_linker/entity_linker.py
whyis_milvus/templates/resource_get.json
whyis_milvus/templates/resource_search.json
whyis_milvus/templates/space_get.json
whyis_milvus/templates/space_search.json
whyis_milvus-0.1.2.dist-info/LICENSE
whyis_milvus-0.1.2.dist-info/METADATA
whyis_milvus-0.1.2.dist-info/WHEEL
whyis_milvus-0.1.2.dist-info/entry_points.txt
whyis_milvus-0.1.2.dist-info/top_level.txt
whyis_milvus-0.1.2.dist-info/RECORD
